ez_manage_tool/__init__.py
ez_manage_tool/app_assets_widget.py
ez_manage_tool/app_assignment_widget.py
ez_manage_tool/app_extra_widget.py
ez_manage_tool/app_history.py
ez_manage_tool/app_home_widget.py
ez_manage_tool/app_main_widget.py
ez_manage_tool/app_projects_widget.py
ez_manage_tool/app_window.py
ez_manage_tool/commands.py
ez_manage_tool/custom_widget.py
ez_manage_tool/main.py
ez_manage_tool/util.py
ez_manage_tool/sources/icons/TV.png
ez_manage_tool/sources/icons/add.png
ez_manage_tool/sources/icons/add2.png
ez_manage_tool/sources/icons/attachment.png
ez_manage_tool/sources/icons/calendar.png
ez_manage_tool/sources/icons/calender.png
ez_manage_tool/sources/icons/camera.png
ez_manage_tool/sources/icons/character.png
ez_manage_tool/sources/icons/checked.png
ez_manage_tool/sources/icons/checked_2.png
ez_manage_tool/sources/icons/close-small.png
ez_manage_tool/sources/icons/close.png
ez_manage_tool/sources/icons/collapse.png
ez_manage_tool/sources/icons/common 3D files ext.PNG
ez_manage_tool/sources/icons/create_project.png
ez_manage_tool/sources/icons/cube.gif
ez_manage_tool/sources/icons/delete.png
ez_manage_tool/sources/icons/delete_timer.png
ez_manage_tool/sources/icons/deselect.png
ez_manage_tool/sources/icons/diamond.png
ez_manage_tool/sources/icons/dice.png
ez_manage_tool/sources/icons/drag.png
ez_manage_tool/sources/icons/edit.png
ez_manage_tool/sources/icons/empty.png
ez_manage_tool/sources/icons/envi.png
ez_manage_tool/sources/icons/exit.png
ez_manage_tool/sources/icons/expand.png
ez_manage_tool/sources/icons/experiment.png
ez_manage_tool/sources/icons/export.png
ez_manage_tool/sources/icons/external_link.png
ez_manage_tool/sources/icons/ez_project.png
ez_manage_tool/sources/icons/ez_project_beta.png
ez_manage_tool/sources/icons/favourite.png
ez_manage_tool/sources/icons/file_.object.png
ez_manage_tool/sources/icons/file_fbx.png
ez_manage_tool/sources/icons/file_ma.png
ez_manage_tool/sources/icons/file_ma_old.png
ez_manage_tool/sources/icons/file_mb.png
EZ_Manage_Tool-1.0.1.dist-info/LICENSE
EZ_Manage_Tool-1.0.1.dist-info/METADATA
EZ_Manage_Tool-1.0.1.dist-info/WHEEL
EZ_Manage_Tool-1.0.1.dist-info/entry_points.txt
EZ_Manage_Tool-1.0.1.dist-info/top_level.txt
EZ_Manage_Tool-1.0.1.dist-info/RECORD
