Metadata-Version: 2.2
Name: EZ_Manage_Tool
Version: 1.0.1
License-File: LICENSE
Requires-Dist: PySide6==6.7.1
Requires-Dist: PySide6_Addons==6.7.1
Requires-Dist: PySide6_Essentials==6.7.1
Requires-Dist: shiboken6==6.7.1
Dynamic: description
Dynamic: description-content-type
Dynamic: requires-dist
